{
  "project_info": {
    "project_number": "253828477443",
    "project_id": "ticknotes-c195b",
    "storage_bucket": "ticknotes-c195b.appspot.com"
  },
  "client": [
    {
      "client_info": {
        "mobilesdk_app_id": "1:253828477443:android:c96a794403cf986af59436",
        "android_client_info": {
          "package_name": "com.example.ticknotes"
        }
      },
      "oauth_client": [
        {
          "client_id": "253828477443-1r9n77o9500huk56f1l1sgjktlac3hlu.apps.googleusercontent.com",
          "client_type": 1,
          "android_info": {
            "package_name": "com.example.ticknotes",
            "certificate_hash": "d8db3cd3329c997d3d19b7d7699cecfa2b1c5c5a"
          }
        },
        {
          "client_id": "253828477443-gvlp40melgm2a99e1fqv40aocn12p0uc.apps.googleusercontent.com",
          "client_type": 3
        }
      ],
      "api_key": [
        {
          "current_key": "AIzaSyDJ1rTrO1TLAg4ReNbBI2EEAMKBWNcIkFk"
        }
      ],
      "services": {
        "appinvite_service": {
          "other_platform_oauth_client": [
            {
              "client_id": "253828477443-gvlp40melgm2a99e1fqv40aocn12p0uc.apps.googleusercontent.com",
              "client_type": 3
            }
          ]
        }
      }
    }
  ],
  "configuration_version": "1"
}